bicorne/__init__.py
bicorne/boucle.py
bicorne/boucleWhile.py
bicorne/condition.py
bicorne/dicoFinal.py
bicorne/dictionnaire.py
bicorne/fonction.py
bicorne/ide.py
bicorne/rand.py
bicorne/tableau.py
bicorne/test.py
bicorne/tryProg.py
bicorne-0.1.dist-info/METADATA
bicorne-0.1.dist-info/WHEEL
bicorne-0.1.dist-info/license.txt
bicorne-0.1.dist-info/top_level.txt
bicorne-0.1.dist-info/RECORD
