Metadata-Version: 2.1
Name: bicorne
Version: 0.1
Summary: apprendre les bases de Python en français
Home-page: https://github.com/BicodeCosmique/bicode
Author: BicodeCosmique
Author-email: gabriel.merville@franklinparis.com
License: MIT
Download-URL: https://github.com/BicodeCosmique/bicode/archive/refs/tags/v_01.tar.gz
Keywords: SOME,MEANINGFULL,BICORNE
Platform: UNKNOWN
Classifier: Development Status :: 3 - Alpha
Classifier: Intended Audience :: Developers
Classifier: Topic :: Software Development :: Build Tools
Classifier: License :: OSI Approved :: MIT License
Requires-Python: >=3.6
License-File: license.txt
